[
    {
        "name": "Barbare"
    },
    {
        "name": "Archer"
    },
    {
        "name": "Gobelin"
    },
    {
        "name": "Géant"
    },
    {
        "name": "Sapeur"
    },
    {
        "name": "Ballon"
    },
    {
        "name": "Sorcier"
    },
    {
        "name": "Guérisseuse"
    },
    {
        "name": "Dragon"
    },
    {
        "name": "P.E.K.K.A"
    },
    {
        "name": "Serviteur"
    },
    {
        "name": "Chevaucheur de cochon"
    },
    {
        "name": "Valkyrie"
    },
    {
        "name": "Golem"
    },
    {
        "name": "Sorcière"
    }
]